LICENSE
README.md
pyproject.toml
setup.py
logging_commons/formatter.py
logging_commons/utils.py
logging_commons.egg-info/PKG-INFO
logging_commons.egg-info/SOURCES.txt
logging_commons.egg-info/dependency_links.txt
logging_commons.egg-info/top_level.txt